easy_dataset_share/.gitignore
easy_dataset_share/__init__.py
easy_dataset_share/canary.py
easy_dataset_share/cli.py
easy_dataset_share/gitignore.py
easy_dataset_share/hashing.py
easy_dataset_share/robots.py
easy_dataset_share/test_data/dataset_1/unmonitored_chunk_00.json
easy_dataset_share/test_data/dataset_1/unmonitored_chunk_01.json
easy_dataset_share/test_data/dataset_1/unmonitored_chunk_02.json
easy_dataset_share/test_data/html_data/example1.html
easy_dataset_share/test_data/html_data/example2.html
easy_dataset_share/test_data/json_data/unmonitored_chunk_00.json
easy_dataset_share/test_data/json_data/unmonitored_chunk_01.json
easy_dataset_share/test_data/json_data/unmonitored_chunk_02.json
easy_dataset_share/test_data/process_data.ipynb
easy_dataset_share/test_data/txt_data/example1.txt
easy_dataset_share/test_data/txt_data/example2.txt
easy_dataset_share/test_data/unmonitored_chunk_00.json
easy_dataset_share/test_data/unmonitored_chunk_01.json
easy_dataset_share/test_data/unmonitored_chunk_02.json
easy_dataset_share/test_data/unmonitored_data.json
easy_dataset_share/tos.py
easy_dataset_share/zipping.py
easy_dataset_share-0.3.1.dist-info/LICENSE
easy_dataset_share-0.3.1.dist-info/METADATA
easy_dataset_share-0.3.1.dist-info/WHEEL
easy_dataset_share-0.3.1.dist-info/entry_points.txt
easy_dataset_share-0.3.1.dist-info/RECORD
