Metadata-Version: 2.3
Name: easy-dataset-share
Version: 0.3.1
Summary: CLI tool to responsibly share datasets by gzipping, canarying, and tracking provenance.
License: Other/Proprietary
Keywords: dataset,sharing,encryption,canary,robots,cli
Author: Edward Turner
Author-email: edward.turner01@outlook.com
Requires-Python: >=3.10,<4.0
Classifier: Development Status :: 3 - Alpha
Classifier: Intended Audience :: Developers
Classifier: Intended Audience :: Science/Research
Classifier: License :: Other/Proprietary License
Classifier: Operating System :: OS Independent
Classifier: Programming Language :: Python :: 3
Classifier: Programming Language :: Python :: 3.10
Classifier: Programming Language :: Python :: 3.11
Classifier: Programming Language :: Python :: 3.12
Classifier: Programming Language :: Python :: 3.13
Classifier: Topic :: Scientific/Engineering :: Information Analysis
Classifier: Topic :: Software Development :: Libraries :: Python Modules
Classifier: Topic :: Utilities
Requires-Dist: click (>=8.0,<9.0)
Requires-Dist: cryptography (>=41.0.0,<42.0.0)
Requires-Dist: requests (>=2.28.0,<3.0.0)
Project-URL: Homepage, https://github.com/Responsible-Dataset-Sharing/easy-dataset-share
Project-URL: Repository, https://github.com/Responsible-Dataset-Sharing/easy-dataset-share
